coomer_xtractor/__init__.py
coomer_xtractor/browser_vars.py
coomer_xtractor/config.py
coomer_xtractor/main.py
coomer_xtractor/actions/__init__.py
coomer_xtractor/actions/jobs.py
coomer_xtractor/menus/__init__.py
coomer_xtractor/menus/main_menu.py
coomer_xtractor/models/__init__.py
coomer_xtractor/models/profiles.py
coomer_xtractor/scrapers/__init__.py
coomer_xtractor/scrapers/add_to_database.py
coomer_xtractor/scrapers/download.py
coomer_xtractor/scrapers/find_files.py
coomer_xtractor/scrapers/find_images.py
coomer_xtractor/scrapers/find_post_pages.py
coomer_xtractor/scrapers/find_videos.py
coomer_xtractor/scrapers/get_top_level_pages.py
coomer_xtractor-0.0.12.dist-info/LICENSE
coomer_xtractor-0.0.12.dist-info/METADATA
coomer_xtractor-0.0.12.dist-info/WHEEL
coomer_xtractor-0.0.12.dist-info/entry_points.txt
coomer_xtractor-0.0.12.dist-info/top_level.txt
coomer_xtractor-0.0.12.dist-info/RECORD
